tianguix/__init__.py
tianguix/order_book.py
tianguix-0.0.2.dist-info/licenses/LICENSE
tianguix-0.0.2.dist-info/METADATA
tianguix-0.0.2.dist-info/WHEEL
tianguix-0.0.2.dist-info/top_level.txt
tianguix-0.0.2.dist-info/RECORD
