Metadata-Version: 2.4
Name: tianguix
Version: 0.0.2
Summary: 'marketplace in a box' - a one-stop shop for all the essential infrastructure and services needed to create a marketplace.
Author-email: "Carlos J. Hernandez" <carlos3.14@gmail.com>
License-Expression: AGPL-3.0-or-later
Project-URL: BugTracker, https://github.com/CarlosJHdez/Tianguix/issues
Project-URL: Documentation, https://tianguix.readthedocs.io/en/latest/
Project-URL: SourceCode, https://github.com/CarlosJHdez/Tianguix
Keywords: market,orderbook,infrastructure,services
Classifier: Development Status :: 3 - Alpha
Classifier: Intended Audience :: Developers
Classifier: Programming Language :: Python :: 3
Classifier: Operating System :: OS Independent
Requires-Python: >=3.6
License-File: LICENSE
Requires-Dist: requests>=2.0
Provides-Extra: testing
Requires-Dist: pytest>=8.0; extra == "testing"
Requires-Dist: pytest-cov>=6.0; extra == "testing"
Dynamic: license-file
